ckastrotools/__init__.py
ckastrotools/__main__.py
ckastrotools/io/__init__.py
ckastrotools/io/subcube.py
ckastrotools/milkyway/__init__.py
ckastrotools/milkyway/coordinates.py
ckastrotools/milkyway/galactic_bar.py
ckastrotools/milkyway/spiralarms.py
ckastrotools/quality/__init__.py
ckastrotools/quality/compare.py
ckastrotools/spectra/__init__.py
ckastrotools/spectra/extract.py
ckastrotools-0.0.8.dist-info/licenses/LICENSE
ckastrotools-0.0.8.dist-info/METADATA
ckastrotools-0.0.8.dist-info/WHEEL
ckastrotools-0.0.8.dist-info/top_level.txt
ckastrotools-0.0.8.dist-info/RECORD
