Metadata-Version: 2.4
Name: ckastrotools
Version: 0.0.8
Summary: General tools for astronomy I personally use regularly for data analysis.
Author: Carsten König
License: MIT License
Project-URL: Homepage, https://gitlab.com/ck2go/ckastrotools
Classifier: Development Status :: 4 - Beta
Classifier: Intended Audience :: Developers
Classifier: License :: OSI Approved :: MIT License
Classifier: Topic :: Software Development
Classifier: Programming Language :: Python
Classifier: Programming Language :: Python :: 3
Requires-Python: >=3.7
License-File: LICENSE
Requires-Dist: spectral-cube
Dynamic: license-file
